tormdb/__init__.py
tormdb/tormdb.py
tormdb-0.0.1.dist-info/WHEEL
tormdb-0.0.1.dist-info/METADATA
tormdb-0.0.1.dist-info/RECORD
