Metadata-Version: 2.1
Name: tormdb
Version: 0.0.1
Summary: 
Home-page: https://github.com/changyuheng/tormdb
License: MPL-2.0
Author: Henry Chang
Author-email: mr.changyuheng@gmail.com
Requires-Python: >=3.8.1,<4.0.0
Classifier: License :: OSI Approved
Classifier: Programming Language :: Python :: 3
Requires-Dist: dataset (>=1.3.2,<2.0.0)
